{
  "date": "2026-01-12",
  "allocations": [
    {
      "assetClass": "Fixed Income",
      "target": 50,
      "current": 0,
      "deviation": 0,
      "rebalancingRequired": false,
      "notes": "Government and investment-grade corporate bonds"
    },
    {
      "assetClass": "Domestic Equities",
      "target": 35,
      "current": 0,
      "deviation": 0,
      "rebalancingRequired": false,
      "notes": "DSE-listed equities"
    },
    {
      "assetClass": "Regional (EAC/SADC) Equities",
      "target": 5,
      "current": 0,
      "deviation": 0,
      "rebalancingRequired": false,
      "notes": "Large-cap liquid issuers"
    },
    {
      "assetClass": "Cash & Cash Equivalents",
      "target": 10,
      "current": 0,
      "deviation": 0,
      "rebalancingRequired": false,
      "notes": "Treasury bills and bank deposits"
    }
  ],
  "securities": [],
  "riskMetrics": [
    {
      "metric": "Single Security Exposure",
      "ipsLimit": "≤10%",
      "currentValue": "0%",
      "status": "Compliant",
      "actionRequired": ""
    },
    {
      "metric": "Single Sector Exposure",
      "ipsLimit": "≤25%",
      "currentValue": "0%",
      "status": "Compliant",
      "actionRequired": ""
    },
    {
      "metric": "Regional Allocation",
      "ipsLimit": "≤10%",
      "currentValue": "0%",
      "status": "Compliant",
      "actionRequired": ""
    },
    {
      "metric": "Weighted Portfolio Duration",
      "ipsLimit": "≤2 yrs",
      "currentValue": "0 yrs",
      "status": "Compliant",
      "actionRequired": ""
    },
    {
      "metric": "Portfolio Volatility",
      "ipsLimit": "5-7% ann.",
      "currentValue": "0%",
      "status": "Compliant",
      "actionRequired": ""
    },
    {
      "metric": "Drawdown Limit",
      "ipsLimit": "≤5%",
      "currentValue": "0%",
      "status": "Compliant",
      "actionRequired": ""
    },
    {
      "metric": "Credit Rating Compliance",
      "ipsLimit": "≥Investment Grade",
      "currentValue": "N/A",
      "status": "Compliant",
      "actionRequired": ""
    }
  ],
  "liquidityItems": [
    {
      "item": "Cash & Cash Equivalents",
      "minimum": 10,
      "maximum": 15,
      "current": 0,
      "status": "Adequate",
      "actionNeeded": "Monitor weekly"
    },
    {
      "item": "Time to Liquidate 80% Portfolio",
      "minimum": 0,
      "maximum": 30,
      "current": 0,
      "status": "Adequate",
      "actionNeeded": "Monitor liquidity conditions"
    },
    {
      "item": "Bid-Ask Spread / Daily Volume",
      "minimum": 0,
      "maximum": 0,
      "current": 0,
      "status": "Adequate",
      "actionNeeded": "Monitor execution efficiency"
    }
  ],
  "tacticalAdjustments": [],
  "performanceMetrics": [
    {
      "metric": "Total Portfolio Return",
      "target": "2-3% (Q1 target)",
      "current": "0%",
      "deviation": "0%",
      "notes": "Target annualized return: 8-12%"
    },
    {
      "metric": "Asset Class Returns",
      "target": "Per allocation",
      "current": "0%",
      "deviation": "0%",
      "notes": "Monitor each asset class separately"
    },
    {
      "metric": "Benchmark-relative Return",
      "target": "Composite Index",
      "current": "0%",
      "deviation": "0%",
      "notes": "35% DSE + 5% Regional + 50% Gov Bonds + 10% T-bill"
    },
    {
      "metric": "Risk-adjusted Metrics",
      "target": "Sharpe & Sortino Ratio",
      "current": "0",
      "deviation": "0",
      "notes": "Calculate monthly"
    }
  ],
  "complianceChecks": [
    {
      "area": "Single Security Limit",
      "ipsLimit": "≤10%",
      "currentStatus": "Compliant",
      "breach": false,
      "actionRequired": ""
    },
    {
      "area": "Single Sector Limit",
      "ipsLimit": "≤25%",
      "currentStatus": "Compliant",
      "breach": false,
      "actionRequired": ""
    },
    {
      "area": "Regional Allocation Limit",
      "ipsLimit": "≤10%",
      "currentStatus": "Compliant",
      "breach": false,
      "actionRequired": ""
    },
    {
      "area": "Drawdown Limit",
      "ipsLimit": "≤5%",
      "currentStatus": "Compliant",
      "breach": false,
      "actionRequired": ""
    },
    {
      "area": "Prohibited Instruments",
      "ipsLimit": "None",
      "currentStatus": "Compliant",
      "breach": false,
      "actionRequired": ""
    },
    {
      "area": "Credit Rating Compliance",
      "ipsLimit": "≥Investment Grade",
      "currentStatus": "Compliant",
      "breach": false,
      "actionRequired": ""
    }
  ]
}
